{
  "Admin": {
    "average_pfstats_latence_1h": {
      "en": "Average latency of supervised applications (1h smoothing)",
      "fr": "Latence moyenne des applications supervisés (lissage 1h)"
    },
    "sum_pfstats_ccnxcount_1h": {
      "en": "Number of connections on supervised applications (1h smoothing)",
      "fr": "Nombre de connexions sur les applications supervisés (lissage 1h)"
    },
    "sum_pfstats_restransmit_1h": {
      "en": "Number of retransmissions on supervised applications (smoothing 1h)",
      "fr": "Nombre de retransmissions sur les applications supervisés (lissage 1h)"
    },

    "pfstats_up": {
      "en": "Bandwidth usage (upload)",
      "fr": "Consommation de données (upload)"
    },
    "pfstats_down": {
      "en": "Bandwidth usage (download)",
      "fr": "Consommation de données (download)"
    },

    "output_wan": {
      "en": "Output wan",
      "fr": "Sortie wan"
    },
    "input_wan": {
      "en": "Input wan",
      "fr": "Entrée wan"
    },

    "largest_connection": {
      "en": "Largest bandwidth connections",
      "fr": "Connexions les plus consommatrices"
    },

    "pfstats_down_with_input_wan_15m": {
      "en": "Bandwidth comparison, professional versus total",
      "fr": "Consommation de bande passante des application métiers par rapport au total"
    }
  },
  "Support": {
    "average_pfstats_latence_1h": {
      "en": "Average latency of supervised applications (1h smoothing)",
      "fr": "Latence moyenne des applications supervisés (lissage 1h)"
    },
    "sum_pfstats_ccnxcount_1h": {
      "en": "Number of connections on supervised applications (1h smoothing)",
      "fr": "Nombre de connexions sur les applications supervisés (lissage 1h)"
    },
    "sum_pfstats_restransmit_1h": {
      "en": "Number of retransmissions on supervised applications (smoothing 1h)",
      "fr": "Nombre de retransmissions sur les applications supervisés (lissage 1h)"
    },

    "pfstats_up": {
      "en": "Bandwidth usage (upload)",
      "fr": "Consommation de données (upload)"
    },
    "pfstats_down": {
      "en": "Bandwidth usage (download)",
      "fr": "Consommation de données (download)"
    },

    "output_wan": {
      "en": "Output wan",
      "fr": "Sortie wan"
    },
    "input_wan": {
      "en": "Input wan",
      "fr": "Entrée wan"
    },

    "largest_connection": {
      "en": "Largest bandwidth connections",
      "fr": "Connexions les plus consommatrices"
    },

    "pfstats_down_with_input_wan_15m": {
      "en": "Bandwidth comparison, professional versus total",
      "fr": "Consommation de bande passante des application métiers par rapport au total"
    }
  },
  "User": {
    "average_pfstats_latence_1h": {
      "en": "Average latency of supervised applications (1h smoothing)",
      "fr": "Latence moyenne des applications supervisés (lissage 1h)"
    },
    "sum_pfstats_ccnxcount_1h": {
      "en": "Number of connections on supervised applications (1h smoothing)",
      "fr": "Nombre de connexions sur les applications supervisés (lissage 1h)"
    },
    "sum_pfstats_restransmit_1h": {
      "en": "Number of retransmissions on supervised applications (smoothing 1h)",
      "fr": "Nombre de retransmissions sur les applications supervisés (lissage 1h)"
    },

    "pfstats_up": {
      "en": "Bandwidth usage (upload)",
      "fr": "Consommation de données (upload)"
    },
    "pfstats_down": {
      "en": "Bandwidth usage (download)",
      "fr": "Consommation de données (download)"
    },

    "output_wan": {
      "en": "Output wan",
      "fr": "Sortie wan"
    },
    "input_wan": {
      "en": "Input wan",
      "fr": "Entrée wan"
    },

    "largest_connection": {
      "en": "Largest bandwidth connections",
      "fr": "Connexions les plus consommatrices"
    },

    "pfstats_down_with_input_wan_15m": {
      "en": "Bandwidth comparison, professional versus total",
      "fr": "Consommation de bande passante des application métiers par rapport au total"
    }
  },
  "Marketing": {},
  "Commercial ": {}
}
